README.rst
setup.py
django_bnr/__init__.py
django_bnr/admin.py
django_bnr/app.py
django_bnr/models.py
django_bnr/utils.py
django_bnr.egg-info/PKG-INFO
django_bnr.egg-info/SOURCES.txt
django_bnr.egg-info/dependency_links.txt
django_bnr.egg-info/requires.txt
django_bnr.egg-info/top_level.txt
django_bnr/management/__init__.py
django_bnr/management/commands/__init__.py
django_bnr/management/commands/get_bnr_rate.py
django_bnr/migrations/0001_initial.py
django_bnr/migrations/__init__.py
django_bnr/south_migrations/0001_initial.py
django_bnr/south_migrations/__init__.py