Metadata-Version: 1.0
Name: django-bnr
Version: 0.2
Summary: BNR exchange rates for django apps.
